[
  {
    "object": "block",
    "id": "1fbecda2-e122-80df-9a48-e0aee9b292eb",
    "parent": {
      "type": "page_id",
      "page_id": "1eeecda2-e122-8019-b0fc-ce3d3e82b5da"
    },
    "type": "heading_1",
    "heading_1": {
      "rich_text": [
        {
          "type": "text",
          "text": {
            "content": "Medical Note"
          },
          "annotations": {
            "bold": false,
            "italic": false,
            "strikethrough": false,
            "underline": false,
            "code": false,
            "color": "default"
          },
          "plain_text": "Medical Note"
        }
      ],
      "color": "default",
      "is_toggleable": false
    },
    "created_time": "2025-05-22T12:50:00Z",
    "created_by": {
      "object": "user",
      "id": "1859a913-3c06-48a0-be9b-01966f93043c"
    },
    "last_edited_time": "2025-05-22T12:50:00Z",
    "last_edited_by": {
      "object": "user",
      "id": "1859a913-3c06-48a0-be9b-01966f93043c"
    },
    "archived": false,
    "has_children": false
  },
  {
    "object": "block",
    "id": "1fbecda2-e122-808c-b87b-f107b910034e",
    "parent": {
      "type": "page_id",
      "page_id": "1eeecda2-e122-8019-b0fc-ce3d3e82b5da"
    },
    "type": "toggle",
    "toggle": {
      "rich_text": [
        {
          "type": "text",
          "text": {
            "content": "Subjective"
          },
          "annotations": {
            "bold": false,
            "italic": false,
            "strikethrough": false,
            "underline": false,
            "code": false,
            "color": "default"
          },
          "plain_text": "Subjective"
        }
      ],
      "color": "default",
      "children": [
        {
          "object": "block",
          "id": "1fbecda2-e122-80d9-852b-cf92b4fba5db",
          "parent": {
            "type": "block_id",
            "block_id": "1fbecda2-e122-808c-b87b-f107b910034e"
          },
          "type": "paragraph",
          "paragraph": {
            "rich_text": [
              {
                "type": "text",
                "text": {
                  "content": "I evaluated Mr. Stiff today for acute respiratory distress. The patient reports feeling unwell since this morning, with progressive worsening of his breathing. He was initially on 3 liters of oxygen with an oxygen saturation of 80%, which prompted me to increase to 6 liters. The patient has a history of hypercapnic respiratory failure with previous IMC (Intermediate Care) admissions. When questioned about the onset of symptoms, he indicated they began this morning after having an \"okay\" night. I noted his condition has deteriorated compared to yesterday's assessment."
                },
                "annotations": {
                  "bold": false,
                  "italic": false,
                  "strikethrough": false,
                  "underline": false,
                  "code": false,
                  "color": "default"
                },
                "plain_text": "I evaluated Mr. Stiff today for acute respiratory distress. The patient reports feeling unwell since this morning, with progressive worsening of his breathing. He was initially on 3 liters of oxygen with an oxygen saturation of 80%, which prompted me to increase to 6 liters. The patient has a history of hypercapnic respiratory failure with previous IMC (Intermediate Care) admissions. When questioned about the onset of symptoms, he indicated they began this morning after having an \"okay\" night. I noted his condition has deteriorated compared to yesterday's assessment."
              }
            ],
            "color": "default"
          },
          "created_time": "2025-05-22T16:27:00Z",
          "created_by": {
            "object": "user",
            "id": "1859a913-3c06-48a0-be9b-01966f93043c"
          },
          "last_edited_time": "2025-05-22T16:27:00Z",
          "last_edited_by": {
            "object": "user",
            "id": "1859a913-3c06-48a0-be9b-01966f93043c"
          },
          "archived": false,
          "has_children": false
        }
      ]
    },
    "created_time": "2025-05-22T12:50:00Z",
    "created_by": {
      "object": "user",
      "id": "1859a913-3c06-48a0-be9b-01966f93043c"
    },
    "last_edited_time": "2025-05-22T16:27:00Z",
    "last_edited_by": {
      "object": "user",
      "id": "1859a913-3c06-48a0-be9b-01966f93043c"
    },
    "archived": false,
    "has_children": true
  },
  {
    "object": "block",
    "id": "1fbecda2-e122-8045-9111-f9d6c52ae4bb",
    "parent": {
      "type": "page_id",
      "page_id": "1eeecda2-e122-8019-b0fc-ce3d3e82b5da"
    },
    "type": "paragraph",
    "paragraph": {
      "rich_text": [],
      "color": "default"
    },
    "created_time": "2025-05-22T12:50:00Z",
    "created_by": {
      "object": "user",
      "id": "1859a913-3c06-48a0-be9b-01966f93043c"
    },
    "last_edited_time": "2025-05-22T16:27:00Z",
    "last_edited_by": {
      "object": "user",
      "id": "1859a913-3c06-48a0-be9b-01966f93043c"
    },
    "archived": false,
    "has_children": false
  },
  {
    "object": "block",
    "id": "1fbecda2-e122-8024-b944-cd27993b1a7f",
    "parent": {
      "type": "page_id",
      "page_id": "1eeecda2-e122-8019-b0fc-ce3d3e82b5da"
    },
    "type": "toggle",
    "toggle": {
      "rich_text": [
        {
          "type": "text",
          "text": {
            "content": "Physical Exam "
          },
          "annotations": {
            "bold": false,
            "italic": false,
            "strikethrough": false,
            "underline": false,
            "code": false,
            "color": "default"
          },
          "plain_text": "Physical Exam "
        }
      ],
      "color": "default",
      "children": [
        {
          "object": "block",
          "id": "1fbecda2-e122-8053-9194-e5704505f3e5",
          "parent": {
            "type": "block_id",
            "block_id": "1fbecda2-e122-8024-b944-cd27993b1a7f"
          },
          "type": "bulleted_list_item",
          "bulleted_list_item": {
            "rich_text": [
              {
                "type": "text",
                "text": {
                  "content": "Respiratory: Moving \"pretty good air\" with no significant wheezing heard"
                },
                "annotations": {
                  "bold": false,
                  "italic": false,
                  "strikethrough": false,
                  "underline": false,
                  "code": false,
                  "color": "default"
                },
                "plain_text": "Respiratory: Moving \"pretty good air\" with no significant wheezing heard"
              }
            ],
            "color": "default"
          },
          "created_time": "2025-05-22T16:28:00Z",
          "created_by": {
            "object": "user",
            "id": "1859a913-3c06-48a0-be9b-01966f93043c"
          },
          "last_edited_time": "2025-05-22T16:28:00Z",
          "last_edited_by": {
            "object": "user",
            "id": "1859a913-3c06-48a0-be9b-01966f93043c"
          },
          "archived": false,
          "has_children": false
        },
        {
          "object": "block",
          "id": "1fbecda2-e122-8057-b145-c9d00ce4147c",
          "parent": {
            "type": "block_id",
            "block_id": "1fbecda2-e122-8024-b944-cd27993b1a7f"
          },
          "type": "bulleted_list_item",
          "bulleted_list_item": {
            "rich_text": [
              {
                "type": "text",
                "text": {
                  "content": "Cardiovascular: Heart murmur present, tachycardia noted"
                },
                "annotations": {
                  "bold": false,
                  "italic": false,
                  "strikethrough": false,
                  "underline": false,
                  "code": false,
                  "color": "default"
                },
                "plain_text": "Cardiovascular: Heart murmur present, tachycardia noted"
              }
            ],
            "color": "default"
          },
          "created_time": "2025-05-22T16:28:00Z",
          "created_by": {
            "object": "user",
            "id": "1859a913-3c06-48a0-be9b-01966f93043c"
          },
          "last_edited_time": "2025-05-22T16:28:00Z",
          "last_edited_by": {
            "object": "user",
            "id": "1859a913-3c06-48a0-be9b-01966f93043c"
          },
          "archived": false,
          "has_children": false
        },
        {
          "object": "block",
          "id": "1fbecda2-e122-80d3-9700-cccd7d881629",
          "parent": {
            "type": "block_id",
            "block_id": "1fbecda2-e122-8024-b944-cd27993b1a7f"
          },
          "type": "bulleted_list_item",
          "bulleted_list_item": {
            "rich_text": [
              {
                "type": "text",
                "text": {
                  "content": "Oxygen: Initially 80% on 3L, increased to 6L, then adjusted to 4L, then 3L"
                },
                "annotations": {
                  "bold": false,
                  "italic": false,
                  "strikethrough": false,
                  "underline": false,
                  "code": false,
                  "color": "default"
                },
                "plain_text": "Oxygen: Initially 80% on 3L, increased to 6L, then adjusted to 4L, then 3L"
              }
            ],
            "color": "default"
          },
          "created_time": "2025-05-22T16:28:00Z",
          "created_by": {
            "object": "user",
            "id": "1859a913-3c06-48a0-be9b-01966f93043c"
          },
          "last_edited_time": "2025-05-22T16:28:00Z",
          "last_edited_by": {
            "object": "user",
            "id": "1859a913-3c06-48a0-be9b-01966f93043c"
          },
          "archived": false,
          "has_children": false
        },
        {
          "object": "block",
          "id": "1fbecda2-e122-80eb-9c6e-e43ce2c92e27",
          "parent": {
            "type": "block_id",
            "block_id": "1fbecda2-e122-8024-b944-cd27993b1a7f"
          },
          "type": "bulleted_list_item",
          "bulleted_list_item": {
            "rich_text": [
              {
                "type": "text",
                "text": {
                  "content": "Mental status: Alert and oriented despite hypercapnia"
                },
                "annotations": {
                  "bold": false,
                  "italic": false,
                  "strikethrough": false,
                  "underline": false,
                  "code": false,
                  "color": "default"
                },
                "plain_text": "Mental status: Alert and oriented despite hypercapnia"
              }
            ],
            "color": "default"
          },
          "created_time": "2025-05-22T16:28:00Z",
          "created_by": {
            "object": "user",
            "id": "1859a913-3c06-48a0-be9b-01966f93043c"
          },
          "last_edited_time": "2025-05-22T16:28:00Z",
          "last_edited_by": {
            "object": "user",
            "id": "1859a913-3c06-48a0-be9b-01966f93043c"
          },
          "archived": false,
          "has_children": false
        },
        {
          "object": "block",
          "id": "1fbecda2-e122-8085-80c6-eeaecfc949b0",
          "parent": {
            "type": "block_id",
            "block_id": "1fbecda2-e122-8024-b944-cd27993b1a7f"
          },
          "type": "bulleted_list_item",
          "bulleted_list_item": {
            "rich_text": [
              {
                "type": "text",
                "text": {
                  "content": "ABG results: 7, 3, 6, 80, 69 - patient is hypercapnic but reasonably compensated"
                },
                "annotations": {
                  "bold": false,
                  "italic": false,
                  "strikethrough": false,
                  "underline": false,
                  "code": false,
                  "color": "default"
                },
                "plain_text": "ABG results: 7, 3, 6, 80, 69 - patient is hypercapnic but reasonably compensated"
              }
            ],
            "color": "default"
          },
          "created_time": "2025-05-22T16:28:00Z",
          "created_by": {
            "object": "user",
            "id": "1859a913-3c06-48a0-be9b-01966f93043c"
          },
          "last_edited_time": "2025-05-22T16:28:00Z",
          "last_edited_by": {
            "object": "user",
            "id": "1859a913-3c06-48a0-be9b-01966f93043c"
          },
          "archived": false,
          "has_children": false
        }
      ]
    },
    "created_time": "2025-05-22T12:50:00Z",
    "created_by": {
      "object": "user",
      "id": "1859a913-3c06-48a0-be9b-01966f93043c"
    },
    "last_edited_time": "2025-05-22T16:28:00Z",
    "last_edited_by": {
      "object": "user",
      "id": "1859a913-3c06-48a0-be9b-01966f93043c"
    },
    "archived": false,
    "has_children": true
  },
  {
    "object": "block",
    "id": "1fbecda2-e122-807b-b00f-e335a16a963c",
    "parent": {
      "type": "page_id",
      "page_id": "1eeecda2-e122-8019-b0fc-ce3d3e82b5da"
    },
    "type": "heading_3",
    "heading_3": {
      "rich_text": [
        {
          "type": "text",
          "text": {
            "content": "Plan"
          },
          "annotations": {
            "bold": false,
            "italic": false,
            "strikethrough": false,
            "underline": false,
            "code": false,
            "color": "default"
          },
          "plain_text": "Plan"
        }
      ],
      "color": "default",
      "is_toggleable": false
    },
    "created_time": "2025-05-22T12:50:00Z",
    "created_by": {
      "object": "user",
      "id": "1859a913-3c06-48a0-be9b-01966f93043c"
    },
    "last_edited_time": "2025-05-22T12:50:00Z",
    "last_edited_by": {
      "object": "user",
      "id": "1859a913-3c06-48a0-be9b-01966f93043c"
    },
    "archived": false,
    "has_children": false
  },
  {
    "object": "block",
    "id": "1fbecda2-e122-809c-97ad-dba3c3af52ba",
    "parent": {
      "type": "page_id",
      "page_id": "1eeecda2-e122-8019-b0fc-ce3d3e82b5da"
    },
    "type": "bulleted_list_item",
    "bulleted_list_item": {
      "rich_text": [
        {
          "type": "text",
          "text": {
            "content": "Chest X-ray ordered and completed"
          },
          "annotations": {
            "bold": false,
            "italic": false,
            "strikethrough": false,
            "underline": false,
            "code": false,
            "color": "default"
          },
          "plain_text": "Chest X-ray ordered and completed"
        }
      ],
      "color": "default"
    },
    "created_time": "2025-05-22T12:50:00Z",
    "created_by": {
      "object": "user",
      "id": "1859a913-3c06-48a0-be9b-01966f93043c"
    },
    "last_edited_time": "2025-05-22T12:50:00Z",
    "last_edited_by": {
      "object": "user",
      "id": "1859a913-3c06-48a0-be9b-01966f93043c"
    },
    "archived": false,
    "has_children": false
  },
  {
    "object": "block",
    "id": "1fbecda2-e122-80d3-a015-d750a6441419",
    "parent": {
      "type": "page_id",
      "page_id": "1eeecda2-e122-8019-b0fc-ce3d3e82b5da"
    },
    "type": "bulleted_list_item",
    "bulleted_list_item": {
      "rich_text": [
        {
          "type": "text",
          "text": {
            "content": "EKG ordered"
          },
          "annotations": {
            "bold": false,
            "italic": false,
            "strikethrough": false,
            "underline": false,
            "code": false,
            "color": "default"
          },
          "plain_text": "EKG ordered"
        }
      ],
      "color": "default"
    },
    "created_time": "2025-05-22T12:50:00Z",
    "created_by": {
      "object": "user",
      "id": "1859a913-3c06-48a0-be9b-01966f93043c"
    },
    "last_edited_time": "2025-05-22T12:50:00Z",
    "last_edited_by": {
      "object": "user",
      "id": "1859a913-3c06-48a0-be9b-01966f93043c"
    },
    "archived": false,
    "has_children": false
  },
  {
    "object": "block",
    "id": "1fbecda2-e122-8092-954a-fa7d07842256",
    "parent": {
      "type": "page_id",
      "page_id": "1eeecda2-e122-8019-b0fc-ce3d3e82b5da"
    },
    "type": "bulleted_list_item",
    "bulleted_list_item": {
      "rich_text": [
        {
          "type": "text",
          "text": {
            "content": "ABG completed - shows hypercapnia with reasonable compensation"
          },
          "annotations": {
            "bold": false,
            "italic": false,
            "strikethrough": false,
            "underline": false,
            "code": false,
            "color": "default"
          },
          "plain_text": "ABG completed - shows hypercapnia with reasonable compensation"
        }
      ],
      "color": "default"
    },
    "created_time": "2025-05-22T12:50:00Z",
    "created_by": {
      "object": "user",
      "id": "1859a913-3c06-48a0-be9b-01966f93043c"
    },
    "last_edited_time": "2025-05-22T12:50:00Z",
    "last_edited_by": {
      "object": "user",
      "id": "1859a913-3c06-48a0-be9b-01966f93043c"
    },
    "archived": false,
    "has_children": false
  },
  {
    "object": "block",
    "id": "1fbecda2-e122-80fe-8024-c3d2f6a7b151",
    "parent": {
      "type": "page_id",
      "page_id": "1eeecda2-e122-8019-b0fc-ce3d3e82b5da"
    },
    "type": "bulleted_list_item",
    "bulleted_list_item": {
      "rich_text": [
        {
          "type": "text",
          "text": {
            "content": "Consider short trial of BiPAP (patient reportedly uses nocturnal BiPAP at home)"
          },
          "annotations": {
            "bold": false,
            "italic": false,
            "strikethrough": false,
            "underline": false,
            "code": false,
            "color": "default"
          },
          "plain_text": "Consider short trial of BiPAP (patient reportedly uses nocturnal BiPAP at home)"
        }
      ],
      "color": "default"
    },
    "created_time": "2025-05-22T12:50:00Z",
    "created_by": {
      "object": "user",
      "id": "1859a913-3c06-48a0-be9b-01966f93043c"
    },
    "last_edited_time": "2025-05-22T12:50:00Z",
    "last_edited_by": {
      "object": "user",
      "id": "1859a913-3c06-48a0-be9b-01966f93043c"
    },
    "archived": false,
    "has_children": false
  },
  {
    "object": "block",
    "id": "1fbecda2-e122-80f1-a0a1-cb00e071bed7",
    "parent": {
      "type": "page_id",
      "page_id": "1eeecda2-e122-8019-b0fc-ce3d3e82b5da"
    },
    "type": "bulleted_list_item",
    "bulleted_list_item": {
      "rich_text": [
        {
          "type": "text",
          "text": {
            "content": "Anticipate transfer to IMC (Intermediate Care) unit"
          },
          "annotations": {
            "bold": false,
            "italic": false,
            "strikethrough": false,
            "underline": false,
            "code": false,
            "color": "default"
          },
          "plain_text": "Anticipate transfer to IMC (Intermediate Care) unit"
        }
      ],
      "color": "default"
    },
    "created_time": "2025-05-22T12:50:00Z",
    "created_by": {
      "object": "user",
      "id": "1859a913-3c06-48a0-be9b-01966f93043c"
    },
    "last_edited_time": "2025-05-22T12:50:00Z",
    "last_edited_by": {
      "object": "user",
      "id": "1859a913-3c06-48a0-be9b-01966f93043c"
    },
    "archived": false,
    "has_children": false
  },
  {
    "object": "block",
    "id": "1fbecda2-e122-80a6-bc25-dd35bb5ad186",
    "parent": {
      "type": "page_id",
      "page_id": "1eeecda2-e122-8019-b0fc-ce3d3e82b5da"
    },
    "type": "bulleted_list_item",
    "bulleted_list_item": {
      "rich_text": [
        {
          "type": "text",
          "text": {
            "content": "Respiratory treatments (previously administered)"
          },
          "annotations": {
            "bold": false,
            "italic": false,
            "strikethrough": false,
            "underline": false,
            "code": false,
            "color": "default"
          },
          "plain_text": "Respiratory treatments (previously administered)"
        }
      ],
      "color": "default"
    },
    "created_time": "2025-05-22T12:50:00Z",
    "created_by": {
      "object": "user",
      "id": "1859a913-3c06-48a0-be9b-01966f93043c"
    },
    "last_edited_time": "2025-05-22T12:50:00Z",
    "last_edited_by": {
      "object": "user",
      "id": "1859a913-3c06-48a0-be9b-01966f93043c"
    },
    "archived": false,
    "has_children": false
  },
  {
    "object": "block",
    "id": "1fbecda2-e122-8049-8b91-d018bbbc2abf",
    "parent": {
      "type": "page_id",
      "page_id": "1eeecda2-e122-8019-b0fc-ce3d3e82b5da"
    },
    "type": "bulleted_list_item",
    "bulleted_list_item": {
      "rich_text": [
        {
          "type": "text",
          "text": {
            "content": "Continue oxygen therapy with titration based on response"
          },
          "annotations": {
            "bold": false,
            "italic": false,
            "strikethrough": false,
            "underline": false,
            "code": false,
            "color": "default"
          },
          "plain_text": "Continue oxygen therapy with titration based on response"
        }
      ],
      "color": "default"
    },
    "created_time": "2025-05-22T12:50:00Z",
    "created_by": {
      "object": "user",
      "id": "1859a913-3c06-48a0-be9b-01966f93043c"
    },
    "last_edited_time": "2025-05-22T12:50:00Z",
    "last_edited_by": {
      "object": "user",
      "id": "1859a913-3c06-48a0-be9b-01966f93043c"
    },
    "archived": false,
    "has_children": false
  },
  {
    "object": "block",
    "id": "1fbecda2-e122-80f0-8ec8-ca60c2af3a11",
    "parent": {
      "type": "page_id",
      "page_id": "1eeecda2-e122-8019-b0fc-ce3d3e82b5da"
    },
    "type": "heading_3",
    "heading_3": {
      "rich_text": [
        {
          "type": "text",
          "text": {
            "content": "Physical Exam"
          },
          "annotations": {
            "bold": false,
            "italic": false,
            "strikethrough": false,
            "underline": false,
            "code": false,
            "color": "default"
          },
          "plain_text": "Physical Exam"
        }
      ],
      "color": "default",
      "is_toggleable": true
    },
    "created_time": "2025-05-22T12:50:00Z",
    "created_by": {
      "object": "user",
      "id": "1859a913-3c06-48a0-be9b-01966f93043c"
    },
    "last_edited_time": "2025-05-22T12:50:00Z",
    "last_edited_by": {
      "object": "user",
      "id": "1859a913-3c06-48a0-be9b-01966f93043c"
    },
    "archived": false,
    "has_children": true
  },
  {
    "object": "block",
    "id": "1fbecda2-e122-8031-8b02-cd5a4f5b35e0",
    "parent": {
      "type": "page_id",
      "page_id": "1eeecda2-e122-8019-b0fc-ce3d3e82b5da"
    },
    "type": "heading_3",
    "heading_3": {
      "rich_text": [
        {
          "type": "text",
          "text": {
            "content": "Hospital Course"
          },
          "annotations": {
            "bold": false,
            "italic": false,
            "strikethrough": false,
            "underline": false,
            "code": false,
            "color": "default"
          },
          "plain_text": "Hospital Course"
        }
      ],
      "color": "default",
      "is_toggleable": true
    },
    "created_time": "2025-05-22T12:50:00Z",
    "created_by": {
      "object": "user",
      "id": "1859a913-3c06-48a0-be9b-01966f93043c"
    },
    "last_edited_time": "2025-05-22T12:50:00Z",
    "last_edited_by": {
      "object": "user",
      "id": "1859a913-3c06-48a0-be9b-01966f93043c"
    },
    "archived": false,
    "has_children": true
  },
  {
    "object": "block",
    "id": "1fbecda2-e122-802c-b5f4-eb93c458c262",
    "parent": {
      "type": "page_id",
      "page_id": "1eeecda2-e122-8019-b0fc-ce3d3e82b5da"
    },
    "type": "heading_3",
    "heading_3": {
      "rich_text": [
        {
          "type": "text",
          "text": {
            "content": "Assessment and Plan"
          },
          "annotations": {
            "bold": false,
            "italic": false,
            "strikethrough": false,
            "underline": false,
            "code": false,
            "color": "default"
          },
          "plain_text": "Assessment and Plan"
        }
      ],
      "color": "default",
      "is_toggleable": true
    },
    "created_time": "2025-05-22T12:50:00Z",
    "created_by": {
      "object": "user",
      "id": "1859a913-3c06-48a0-be9b-01966f93043c"
    },
    "last_edited_time": "2025-05-22T12:50:00Z",
    "last_edited_by": {
      "object": "user",
      "id": "1859a913-3c06-48a0-be9b-01966f93043c"
    },
    "archived": false,
    "has_children": true
  }
]